<annotation>
	<folder>telo kuning</folder>
	<filename>IMG_20211002_142331.jpg</filename>
	<path>C:\ARKA\KULIAH\SMST 7\Objek deteksi\telo kuning\IMG_20211002_142331.jpg</path>
	<source>
		<database>Unknown</database>
	</source>
	<size>
		<width>2592</width>
		<height>1944</height>
		<depth>3</depth>
	</size>
	<segmented>0</segmented>
	<object>
		<name>ubi kuning</name>
		<pose>Unspecified</pose>
		<truncated>0</truncated>
		<difficult>0</difficult>
		<bndbox>
			<xmin>698</xmin>
			<ymin>920</ymin>
			<xmax>1335</xmax>
			<ymax>1593</ymax>
		</bndbox>
	</object>
	<object>
		<name>ubi kuning</name>
		<pose>Unspecified</pose>
		<truncated>0</truncated>
		<difficult>0</difficult>
		<bndbox>
			<xmin>1316</xmin>
			<ymin>768</ymin>
			<xmax>1902</xmax>
			<ymax>1464</ymax>
		</bndbox>
	</object>
	<object>
		<name>ubi kuning</name>
		<pose>Unspecified</pose>
		<truncated>0</truncated>
		<difficult>0</difficult>
		<bndbox>
			<xmin>1779</xmin>
			<ymin>679</ymin>
			<xmax>2449</xmax>
			<ymax>1332</ymax>
		</bndbox>
	</object>
	<object>
		<name>ubi kuning</name>
		<pose>Unspecified</pose>
		<truncated>0</truncated>
		<difficult>0</difficult>
		<bndbox>
			<xmin>937</xmin>
			<ymin>315</ymin>
			<xmax>1577</xmax>
			<ymax>1026</ymax>
		</bndbox>
	</object>
	<object>
		<name>ubi kuning</name>
		<pose>Unspecified</pose>
		<truncated>0</truncated>
		<difficult>0</difficult>
		<bndbox>
			<xmin>1514</xmin>
			<ymin>222</ymin>
			<xmax>2420</xmax>
			<ymax>795</ymax>
		</bndbox>
	</object>
	<object>
		<name>ubi kuning</name>
		<pose>Unspecified</pose>
		<truncated>0</truncated>
		<difficult>0</difficult>
		<bndbox>
			<xmin>1322</xmin>
			<ymin>683</ymin>
			<xmax>2534</xmax>
			<ymax>1444</ymax>
		</bndbox>
	</object>
</annotation>
